ccreload/Signal.py
ccreload/__init__.py
ccreload/autoreload.py
ccreload/reloadDeco.py
ccreload-1.1.dist-info/METADATA
ccreload-1.1.dist-info/WHEEL
ccreload-1.1.dist-info/top_level.txt
ccreload-1.1.dist-info/RECORD
